cursor_rag/__init__.py
cursor_rag/chunking.py
cursor_rag/cli.py
cursor_rag/config.py
cursor_rag/indexer.py
cursor_rag/mcp_server.py
cursor_rag_tools-1.0.3.dist-info/licenses/LICENSE
cursor_rag_tools-1.0.3.dist-info/METADATA
cursor_rag_tools-1.0.3.dist-info/WHEEL
cursor_rag_tools-1.0.3.dist-info/entry_points.txt
cursor_rag_tools-1.0.3.dist-info/top_level.txt
cursor_rag_tools-1.0.3.dist-info/RECORD
