Metadata-Version: 2.4
Name: cursor-rag-tools
Version: 1.0.3
Summary: RAG indexing and search for Cursor IDE via MCP
Author: Cursor RAG Tools Contributors
License: MIT
Project-URL: Homepage, https://github.com/your-org/cursor-rag-tools
Project-URL: Repository, https://github.com/your-org/cursor-rag-tools
Project-URL: Issues, https://github.com/your-org/cursor-rag-tools/issues
Keywords: rag,cursor,mcp,indexing,chromadb,ai
Classifier: Development Status :: 4 - Beta
Classifier: Intended Audience :: Developers
Classifier: License :: OSI Approved :: MIT License
Classifier: Programming Language :: Python :: 3
Classifier: Programming Language :: Python :: 3.11
Classifier: Programming Language :: Python :: 3.12
Requires-Python: >=3.11
License-File: LICENSE
Requires-Dist: chromadb>=0.4.0
Requires-Dist: sentence-transformers>=2.0.0
Requires-Dist: mcp>=0.9.0
Provides-Extra: dev
Requires-Dist: pytest>=7.0.0; extra == "dev"
Requires-Dist: black>=23.0.0; extra == "dev"
Requires-Dist: ruff>=0.1.0; extra == "dev"
Provides-Extra: parsers
Requires-Dist: tree-sitter>=0.21.3; extra == "parsers"
Requires-Dist: tree_sitter_languages>=1.10.2; python_version < "3.13" and extra == "parsers"
Dynamic: license-file
